{
  "posts": [
    {
      "title": "last post",
      "email": "1@3.c",
      "content": "ggggggggggggggggggggggggggggggg",
      "id": 3
    }
  ],
  "comments": [
    {
      "commentcontent": " nnnnn",
      "postid": "1",
      "cname": "dafffaa",
      "id": 2
    },
    {
      "commentcontent": "hhhh",
      "postid": "2",
      "cname": "dafffaa",
      "id": 3
    },
    {
      "commentcontent": "ggg",
      "postid": "2",
      "cname": "dafffaa",
      "id": 4
    },
    {
      "id": 5
    },
    {
      "commentcontent": "ggg",
      "postid": "1",
      "cname": "dafffaa",
      "id": 6
    }
  ],
  "profile": [
    {
      "name": "test",
      "email": "1@3.c",
      "pass": "123456",
      "id": 1
    },
    {
      "name": "test",
      "email": "1@3.c",
      "pass": "123456",
      "id": 2
    },
    {
      "test": [
        "",
        ""
      ],
      "id": 3
    },
    {
      "id": 4
    },
    {
      "id": 5
    },
    {
      "id": 6
    },
    {
      "id": 7
    }
  ]
}